GoogleWalletPassGenerator/__init__.py
GoogleWalletPassGenerator/enums.py
GoogleWalletPassGenerator/eventticket.py
GoogleWalletPassGenerator/serializer.py
GoogleWalletPassGenerator/types.py
GoogleWalletPassGenerator-1.1.6.dist-info/LICENSE
GoogleWalletPassGenerator-1.1.6.dist-info/METADATA
GoogleWalletPassGenerator-1.1.6.dist-info/WHEEL
GoogleWalletPassGenerator-1.1.6.dist-info/top_level.txt
GoogleWalletPassGenerator-1.1.6.dist-info/RECORD
