Metadata-Version: 2.1
Name: GoogleWalletPassGenerator
Version: 1.1.6
Summary: A useful package to help you create Google Wallet Passes.
Home-page: https://github.com/gianlucapirro/GoogleWalletPassGenerator
Download-URL: https://github.com/gianlucapirro/GoogleWalletPassGenerator/archive/refs/tags/v1.1.6.tar.gz
Author: Gian Luca Pirro
Author-email: gianlucap2003@gmail.com
License: MIT
License-File: LICENSE
Requires-Dist: requests
Requires-Dist: google-auth
Requires-Dist: google-auth-oauthlib
Requires-Dist: google-auth-httplib2
